HISTORY.txt
LICENSE.txt
MANIFEST.in
README.md
setup.cfg
setup.py
sparc/__init__.py
sparc.testing.egg-info/PKG-INFO
sparc.testing.egg-info/SOURCES.txt
sparc.testing.egg-info/dependency_links.txt
sparc.testing.egg-info/entry_points.txt
sparc.testing.egg-info/namespace_packages.txt
sparc.testing.egg-info/not-zip-safe
sparc.testing.egg-info/requires.txt
sparc.testing.egg-info/top_level.txt
sparc/testing/__init__.py
sparc/testing/configure.zcml
sparc/testing/fixture.py
sparc/testing/ftesting.zcml
sparc/testing/testlayer.py