Metadata-Version: 1.1
Name: sparc.testing
Version: 0.0.3
Summary: testing for the SPARC platform
Home-page: https://github.com/davisd50/sparc.testing
Author: David Davis
Author-email: davisd50@gmail.com
License: MIT
Keywords: zca
Platform: UNKNOWN
Classifier: Development Status :: 2 - Pre-Alpha
Classifier: Intended Audience :: Developers
Classifier: License :: OSI Approved :: MIT License
Classifier: Natural Language :: English
Classifier: Framework :: Zope3
Classifier: Programming Language :: Python :: 2
Classifier: Programming Language :: Python :: 2.7
Classifier: Programming Language :: Python :: 3
